atm_controller.v
module atm_controller #(
    parameter MAX_PIN_ATTEMPTS = 3
)(
    input clk,
    input rst,
    input card_inserted,
    input pin_valid,
    input pin_invalid,
    input txn_select,
    input amount_valid,
    input cash_available,
    input cash_taken,
    input cancel,

    output reg card_eject,
    output reg card_retain,
    output reg cash_dispense,
    output reg receipt_print,
    output reg error,
    output [3:0] state_dbg
);

parameter S_IDLE        = 4'd0,
          S_CARD_IN     = 4'd1,
          S_PIN_CHECK   = 4'd2,
          S_MENU        = 4'd3,
          S_AMOUNT      = 4'd4,
          S_DISPENSE    = 4'd5,
          S_RECEIPT     = 4'd6,
          S_EJECT       = 4'd7,
          S_ERROR       = 4'd8,
          S_RETAIN_CARD = 4'd9;

reg [3:0] state;
reg [3:0] next_state;
reg [1:0] pin_attempts;
reg pin_retry_error;

assign state_dbg = state;

always @(posedge clk) begin
    if (rst) begin
        state <= S_IDLE;
        pin_attempts <= 2'd0;
        pin_retry_error <= 1'b0;
    end
    else begin
        state <= next_state;

        if ((state == S_IDLE) ||
            ((state == S_PIN_CHECK) && pin_valid))
            pin_attempts <= 2'd0;

        else if ((state == S_PIN_CHECK) && pin_invalid)
            pin_attempts <= pin_attempts + 1'b1;

        if ((state == S_PIN_CHECK) && pin_invalid)
            pin_retry_error <= 1'b1;

        else if ((state == S_AMOUNT) &&
                 amount_valid &&
                 !cash_available)
            pin_retry_error <= 1'b0;

        else if (state == S_IDLE)
            pin_retry_error <= 1'b0;
    end
end

always @(*) begin
    next_state = state;

    card_eject    = 1'b0;
    card_retain   = 1'b0;
    cash_dispense = 1'b0;
    receipt_print = 1'b0;
    error         = 1'b0;

    case (state)

        S_IDLE: begin
            if (card_inserted)
                next_state = S_CARD_IN;
        end

        S_CARD_IN: begin
            if (cancel)
                next_state = S_EJECT;
            else
                next_state = S_PIN_CHECK;
        end

        S_PIN_CHECK: begin
            if (cancel)
                next_state = S_EJECT;

            else if (pin_valid)
                next_state = S_MENU;

            else if (pin_invalid) begin
                if (pin_attempts == MAX_PIN_ATTEMPTS - 1)
                    next_state = S_RETAIN_CARD;
                else
                    next_state = S_ERROR;
            end
        end

        S_MENU: begin
            if (cancel)
                next_state = S_EJECT;

            else if (txn_select)
                next_state = S_AMOUNT;
        end

        S_AMOUNT: begin
            if (cancel)
                next_state = S_EJECT;

            else if (amount_valid) begin
                if (cash_available)
                    next_state = S_DISPENSE;
                else
                    next_state = S_ERROR;
            end
        end

        S_DISPENSE: begin
            cash_dispense = 1'b1;

            if (cancel)
                next_state = S_EJECT;

            else if (cash_taken)
                next_state = S_RECEIPT;
        end

        S_RECEIPT: begin
            receipt_print = 1'b1;
            next_state = S_EJECT;
        end

        S_EJECT: begin
            card_eject = 1'b1;
            next_state = S_IDLE;
        end

        S_ERROR: begin
            error = 1'b1;

            if (pin_retry_error)
                next_state = S_PIN_CHECK;
            else
                next_state = S_EJECT;
        end

        S_RETAIN_CARD: begin
            card_retain = 1'b1;
            next_state = S_IDLE;
        end

        default: begin
            next_state = S_IDLE;
        end

    endcase
end

endmodule

tb_atm_controller.v
module tb_atm_controller;

reg clk;
reg rst;
reg card_inserted;
reg pin_valid;
reg pin_invalid;
reg txn_select;
reg amount_valid;
reg cash_available;
reg cash_taken;
reg cancel;

wire card_eject;
wire card_retain;
wire cash_dispense;
wire receipt_print;
wire error;
wire [3:0] state_dbg;

atm_controller uut (
    .clk(clk),
    .rst(rst),
    .card_inserted(card_inserted),
    .pin_valid(pin_valid),
    .pin_invalid(pin_invalid),
    .txn_select(txn_select),
    .amount_valid(amount_valid),
    .cash_available(cash_available),
    .cash_taken(cash_taken),
    .cancel(cancel),
    .card_eject(card_eject),
    .card_retain(card_retain),
    .cash_dispense(cash_dispense),
    .receipt_print(receipt_print),
    .error(error),
    .state_dbg(state_dbg)
);

always #5 clk = ~clk;

initial begin
    $dumpfile("wave_atm_controller.vcd");
    $dumpvars(0, tb_atm_controller);

    clk = 0;
    rst = 0;
    card_inserted = 0;
    pin_valid = 0;
    pin_invalid = 0;
    txn_select = 0;
    amount_valid = 0;
    cash_available = 0;
    cash_taken = 0;
    cancel = 0;

    rst = 1;
    #10;
    rst = 0;

    $display("===== Successful Withdrawal Test =====");

    card_inserted = 1;
    #10;
    card_inserted = 0;

    pin_valid = 1;
    #10;
    pin_valid = 0;

    txn_select = 1;
    #10;
    txn_select = 0;

    amount_valid = 1;
    cash_available = 1;
    #10;
    amount_valid = 0;
    cash_available = 0;

    #10;

    cash_taken = 1;
    #10;
    cash_taken = 0;

    #20;

    $display("===== Invalid PIN Retry Test =====");

    card_inserted = 1;
    #10;
    card_inserted = 0;

    pin_invalid = 1;
    #10;
    pin_invalid = 0;

    #20;

    pin_invalid = 1;
    #10;
    pin_invalid = 0;

    #20;

    pin_invalid = 1;
    #10;
    pin_invalid = 0;

    #20;

    $display("===== Cash Unavailable Test =====");

    rst = 1;
    #10;
    rst = 0;

    card_inserted = 1;
    #10;
    card_inserted = 0;

    pin_valid = 1;
    #10;
    pin_valid = 0;

    txn_select = 1;
    #10;
    txn_select = 0;

    amount_valid = 1;
    cash_available = 0;
    #10;
    amount_valid = 0;

    #30;

    $display("===== Cancel Test =====");

    rst = 1;
    #10;
    rst = 0;

    card_inserted = 1;
    #10;
    card_inserted = 0;

    pin_valid = 1;
    #10;
    pin_valid = 0;

    txn_select = 1;
    #10;
    txn_select = 0;

    cancel = 1;
    #10;
    cancel = 0;

    #30;

    $display("Simulation Completed");
    $finish;
end

endmodule

wave_atm_controller.vcd
$date
	Sun Jun 14 23:48:44 2026
$end
$version
	Icarus Verilog
$end
$timescale
	1s
$end
$scope module tb_atm_controller $end
$var wire 4 ! state_dbg [3:0] $end
$var wire 1 " receipt_print $end
$var wire 1 # error $end
$var wire 1 $ cash_dispense $end
$var wire 1 % card_retain $end
$var wire 1 & card_eject $end
$var reg 1 ' amount_valid $end
$var reg 1 ( cancel $end
$var reg 1 ) card_inserted $end
$var reg 1 * cash_available $end
$var reg 1 + cash_taken $end
$var reg 1 , clk $end
$var reg 1 - pin_invalid $end
$var reg 1 . pin_valid $end
$var reg 1 / rst $end
$var reg 1 0 txn_select $end
$scope module uut $end
$var wire 1 ' amount_valid $end
$var wire 1 ( cancel $end
$var wire 1 ) card_inserted $end
$var wire 1 * cash_available $end
$var wire 1 + cash_taken $end
$var wire 1 , clk $end
$var wire 1 - pin_invalid $end
$var wire 1 . pin_valid $end
$var wire 1 / rst $end
$var wire 4 1 state_dbg [3:0] $end
$var wire 1 0 txn_select $end
$var parameter 32 2 MAX_PIN_ATTEMPTS $end
$var parameter 4 3 S_AMOUNT $end
$var parameter 4 4 S_CARD_IN $end
$var parameter 4 5 S_DISPENSE $end
$var parameter 4 6 S_EJECT $end
$var parameter 4 7 S_ERROR $end
$var parameter 4 8 S_IDLE $end
$var parameter 4 9 S_MENU $end
$var parameter 4 : S_PIN_CHECK $end
$var parameter 4 ; S_RECEIPT $end
$var parameter 4 < S_RETAIN_CARD $end
$var reg 1 & card_eject $end
$var reg 1 % card_retain $end
$var reg 1 $ cash_dispense $end
$var reg 1 # error $end
$var reg 4 = next_state [3:0] $end
$var reg 2 > pin_attempts [1:0] $end
$var reg 1 ? pin_retry_error $end
$var reg 1 " receipt_print $end
$var reg 4 @ state [3:0] $end
$upscope $end
$upscope $end
$enddefinitions $end
$comment Show the parameter values. $end
$dumpall
b1001 <
b110 ;
b10 :
b11 9
b0 8
b1000 7
b111 6
b101 5
b1 4
b100 3
b11 2
$end
#0
$dumpvars
bx @
x?
bx >
b0 =
bx 1
00
1/
0.
0-
0,
0+
0*
0)
0(
0'
0&
0%
0$
0#
0"
bx !
$end
#5
0?
b0 >
b0 !
b0 1
b0 @
1,
#10
b1 =
0,
1)
0/
#15
b10 =
b1 !
b1 1
b1 @
1,
#20
b10 =
0,
1.
0)
#25
b11 =
b10 !
b10 1
b10 @
1,
#30
b10 =
0,
10
0.
#35
1,
#40
0,
1*
1'
00
#45
1,
#50
0,
0*
0'
#55
1,
#60
0,
1+
#65
1,
#70
0,
0+
#75
1,
#80
0,
#85
1,
#90
0,
1)
#95
1,
#100
b1000 =
0,
1-
0)
#105
b10 =
1#
1?
b1 >
b1000 !
b1000 1
b1000 @
1,
#110
1#
b10 =
0,
0-
#115
0#
b10 !
b10 1
b10 @
1,
#120
0,
#125
1,
#130
b1000 =
0,
1-
#135
b10 =
1#
b10 >
b1000 !
b1000 1
b1000 @
1,
#140
1#
b10 =
0,
0-
#145
0#
b10 !
b10 1
b10 @
1,
#150
0,
#155
1,
#160
b1001 =
0,
1-
#165
b0 =
1%
b11 >
b1001 !
b1001 1
b1001 @
1,
#170
1%
b0 =
0,
0-
#175
0%
b0 !
b0 1
b0 @
1,
#180
0,
#185
0?
b0 >
1,
#190
0,
1/
#195
1,
#200
b1 =
0,
1)
0/
#205
b10 =
b1 !
b1 1
b1 @
1,
#210
b10 =
0,
1.
0)
#215
b11 =
b10 !
b10 1
b10 @
1,
#220
b10 =
0,
10
0.
#225
1,
#230
0,
1'
00
#235
1,
#240
0,
0'
#245
1,
#250
0,
#255
1,
#260
0,
#265
1,
#270
0,
1/
#275
b0 =
b0 !
b0 1
b0 @
1,
#280
b1 =
0,
1)
0/
#285
b10 =
b1 !
b1 1
b1 @
1,
#290
b10 =
0,
1.
0)
#295
b11 =
b10 !
b10 1
b10 @
1,
#300
b10 =
0,
10
0.
#305
1,
#310
b111 =
0,
1(
00
#315
b0 =
1&
b111 !
b111 1
b111 @
1,
#320
1&
b0 =
0,
0(
#325
0&
b0 !
b0 1
b0 @
1,
